baczy/__init__.py
baczy/__main__.py
baczy/baczy.CITATION
baczy/baczy.LICENSE
baczy/baczy.VERSION
baczy/setup.py
baczy/config/config.yaml
baczy/workflow/Snakefile
baczy/workflow/envs/defensefinder.yaml
baczy/workflow/envs/phispy.yaml
baczy/workflow/rules/0.preflight.smk
baczy/workflow/rules/1.fastp.smk
baczy/workflow/rules/2.hybracter.smk
baczy/workflow/rules/2.megahit.smk
baczy/workflow/rules/3.bakta.smk
baczy/workflow/rules/4.amrfinder.smk
baczy/workflow/rules/4.phispy.smk
baczy/workflow/rules/5.defensefinder.smk
baczy/workflow/rules/6.gtdbtk.smk
baczy/workflow/rules/7.capsulefinder.smk
baczy/workflow/rules/8.summary-long.smk
baczy/workflow/rules/8.summary-short.smk
baczy/workflow/rules/9.panaroo-long.smk
baczy/workflow/rules/9.panaroo-short.smk
baczy/workflow/rules/99.targets.smk
baczy/workflow/scripts/hybractercsv.py
baczy/workflow/scripts/merge_bakta.py
baczy-1.0.3.dist-info/METADATA
baczy-1.0.3.dist-info/WHEEL
baczy-1.0.3.dist-info/entry_points.txt
baczy-1.0.3.dist-info/top_level.txt
baczy-1.0.3.dist-info/RECORD
