Metadata-Version: 2.2
Name: baczy
Version: 1.0.3
Summary: Bacterial assembly and annotation
Author-email: Bhavya Papudeshi <npbhavya13@gmail.com>
License: MIT
Keywords: bioinformatics,assembly,annotation,bacteria
Classifier: Environment :: Console
Classifier: Environment :: MacOS X
Classifier: Intended Audience :: Science/Research
Classifier: License :: OSI Approved :: MIT License
Classifier: Natural Language :: English
Classifier: Operating System :: POSIX :: Linux
Classifier: Operating System :: MacOS :: MacOS X
Classifier: Programming Language :: Python :: 3.12
Classifier: Topic :: Scientific/Engineering :: Bio-Informatics
Requires-Python: >=3.9
Requires-Dist: snaketool-utils>=0.0.5
Requires-Dist: snakemake>=8.28.0
Requires-Dist: pyyaml>=6.0
Requires-Dist: Click>=8.1.3
Requires-Dist: metasnek>=0.0.8
Requires-Dist: pandas
